{
  "FR": ["Paris", "Nice", "Lyon", "Marseille", "Bordeaux", "Toulouse", "Cannes"],
  "ES": ["Barcelona", "Madrid", "Seville", "Valencia", "Granada", "Bilbao", "Malaga"],
  "IT": ["Rome", "Venice", "Florence", "Milan", "Naples", "Pisa", "Verona"],
  "GB": ["London", "Manchester", "Edinburgh", "Liverpool", "Birmingham", "Oxford", "Cambridge"],
  "TR": ["Istanbul", "Antalya", "Cappadocia", "Ankara", "Izmir", "Bodrum", "Pamukkale"],
  "DE": ["Berlin", "Munich", "Frankfurt", "Hamburg", "Cologne", "Stuttgart", "Dresden"],
  "GR": ["Athens", "Santorini", "Mykonos", "Crete", "Rhodes", "Corfu", "Thessaloniki"],
  "CH": ["Zurich", "Geneva", "Lucerne", "Interlaken", "Bern", "Lausanne", "Zermatt"],
  "AE": ["Dubai", "Abu Dhabi", "Sharjah", "Ras Al Khaimah", "Fujairah", "Ajman", "Al Ain"],
  "TH": ["Bangkok", "Phuket", "Chiang Mai", "Pattaya", "Krabi", "Koh Samui", "Ayutthaya"],
  "MY": ["Kuala Lumpur", "Penang", "Langkawi", "Malacca", "Kota Kinabalu", "Johor Bahru", "Ipoh"],
  "SG": ["Singapore", "Sentosa Island", "Marina Bay", "Chinatown", "Little India", "Clarke Quay", "Gardens by the Bay"],
  "ID": ["Bali", "Jakarta", "Yogyakarta", "Lombok", "Bandung", "Surabaya", "Medan"],
  "JP": ["Tokyo", "Kyoto", "Osaka", "Hokkaido", "Hiroshima", "Nara", "Fukuoka"],
  "CN": ["Beijing", "Shanghai", "Guangzhou", "Shenzhen", "Xi'an", "Chengdu", "Hangzhou"],
  "US": ["New York", "Los Angeles", "Las Vegas", "Miami", "San Francisco", "Chicago", "Orlando"],
  "CA": ["Toronto", "Vancouver", "Montreal", "Calgary", "Ottawa", "Quebec City", "Banff"],
  "BR": ["Rio de Janeiro", "São Paulo", "Brasília", "Salvador", "Fortaleza", "Recife", "Curitiba"],
  "AU": ["Sydney", "Melbourne", "Brisbane", "Perth", "Adelaide", "Gold Coast", "Cairns"],
  "NZ": ["Auckland", "Queenstown", "Christchurch", "Wellington", "Rotorua", "Dunedin", "Taupo"],
  "EG": ["Cairo", "Luxor", "Aswan", "Sharm El Sheikh", "Alexandria", "Hurghada", "Giza"],
  "ZA": ["Cape Town", "Johannesburg", "Durban", "Pretoria", "Port Elizabeth", "Kruger National Park", "Stellenbosch"],
  "IN": ["Delhi", "Mumbai", "Goa", "Jaipur", "Agra", "Kerala", "Varanasi"],
  "LK": ["Colombo", "Kandy", "Galle", "Nuwara Eliya", "Bentota", "Jaffna", "Sigiriya"],
  "MV": ["Male", "Maafushi", "Addu City", "Fuvahmulah", "Dhigurah", "Thulusdhoo", "Hulhumale"]
}
